graph_examples/__init__.py
graph_examples-0.0.1.dist-info/LICENSE
graph_examples-0.0.1.dist-info/METADATA
graph_examples-0.0.1.dist-info/WHEEL
graph_examples-0.0.1.dist-info/top_level.txt
graph_examples-0.0.1.dist-info/RECORD
